reddwarf/__init__.py
reddwarf/agora.py
reddwarf/data_loader.py
reddwarf/data_presenter.py
reddwarf/exceptions.py
reddwarf/helpers.py
reddwarf/models.py
reddwarf/polis.py
reddwarf/utils.py
reddwarf/types/__init__.py
reddwarf/types/agora.py
red_dwarf_democracy-0.1.1.dist-info/METADATA
red_dwarf_democracy-0.1.1.dist-info/WHEEL
red_dwarf_democracy-0.1.1.dist-info/top_level.txt
red_dwarf_democracy-0.1.1.dist-info/RECORD
