Metadata-Version: 2.2
Name: red-dwarf-democracy
Version: 0.1.1
Summary: A dimensional reduction library for stellarpunk democracy into the long haul
Requires-Python: >=3.10
Requires-Dist: fake-useragent>=2.0.3
Requires-Dist: matplotlib>=3.10.0
Requires-Dist: pandas>=2.2.2
Requires-Dist: requests-cache
Requires-Dist: requests>=2.32.3
Requires-Dist: scikit-learn>=1.6.0
Requires-Dist: requests-ratelimiter>=0.7.0
Requires-Dist: concave-hull>=0.0.9
Requires-Dist: seaborn>=0.13.2
Requires-Dist: pydantic>=2.10.6
Provides-Extra: dev
Requires-Dist: pytest>=8.3.4; extra == "dev"
